sims/__init__.py
sims/_version.py
sims/interface.py
sims/likelihoods.py
sims/instruments/__init__.py
sims/instruments/thomson.py
sim_solps-0.1.3.dist-info/LICENSE
sim_solps-0.1.3.dist-info/METADATA
sim_solps-0.1.3.dist-info/WHEEL
sim_solps-0.1.3.dist-info/top_level.txt
sim_solps-0.1.3.dist-info/RECORD
