Metadata-Version: 2.1
Name: sim-solps
Version: 0.1.3
Summary: Synthetic instrument modelling for SOLPS-ITER
Author-email: Chris Bowman <chris.bowman.physics@gmail.com>
License: MIT License
Project-URL: Homepage, https://github.com/C-bowman/sim-solps
Project-URL: Documentation, https://sim-solps.readthedocs.io/en/stable/
Classifier: Programming Language :: Python :: 3
Classifier: License :: OSI Approved :: MIT License
Classifier: Operating System :: OS Independent
Requires-Python: >=3.9
License-File: LICENSE
Requires-Dist: numpy >=1.20
Requires-Dist: scipy >=1.6.3
Requires-Dist: matplotlib >=3.4.2
Requires-Dist: tokamesh >=0.4.1
Provides-Extra: tests
Requires-Dist: pytest >=3.3.0 ; extra == 'tests'
